{
    "title": "Konchuki",
    "description": "One day, a boy who loves Insects, \"Anri Kajimi,\" meets \"Makiri Oka,\" an Insect girl (Konchuki) who came from 100 years into the future. Oka, who is a \"Konchuki\" with the characteristics of both a human being and a insect, presses him into \"mating with her\".",
    "author": "Murata Shinya",
    "artist": "zunta",
    "cover": "https://files.catbox.moe/7pqdo5.png",
    "chapters": {
        "1": {
            "title": "I Want Us To Have Sex",
            "volume": "1",
            "groups": {
                "orchesc/a/ns": "/proxy/api/catbox/pudw9a"
            },
            "last_updated": 1593896805
        },
        "2": {
            "title": "Dear Mr. Penis",
            "volume": "1",
            "groups": {
                "orchesc/a/ns": "/proxy/api/catbox/zs4wzb"
            },
            "last_updated": 1602882259
        },
        "3": {
            "title": "That's Totally Not Normal, Right?",
            "volume": "1",
            "groups": {
                "orchesc/a/ns": "/proxy/api/catbox/j40id6"
            },
            "last_updated": 1660955953
        },
        "4": {
            "title": "The Disturbance of Public Morals",
            "volume": "2",
            "groups": {
                "orchesc/a/ns": "/proxy/api/catbox/pu7un6"
            },
            "last_updated": 1660956014
        },
        "5": {
            "title": "Choose Any Hole You Like",
            "volume": "2",
            "groups": {
                "orchesc/a/ns": "/proxy/api/catbox/fiu0vl"
            },
            "last_updated": 1660956026
        },
        "6": {
            "title": "The Cum Grail War",
            "volume": "2",
            "groups": {
                "orchesc/a/ns": "/proxy/api/catbox/0tu8b1"
            },
            "last_updated": 1660956032
        },
        "7": {
            "title": "Cicada Bomb",
            "volume": "2",
            "groups": {
                "orchesc/a/ns": "/proxy/api/catbox/7i4hhd"
            },
            "last_updated": 1660955896
        },
        "8": {
            "title": "Eye for an Eye, Human for...",
            "volume": "2",
            "groups": {
                "orchesc/a/ns": "/proxy/api/catbox/9ndivs"
            },
            "last_updated": 1660955907
        },
        "9": {
            "title": "Insect Lovers' Destiny",
            "volume": "2",
            "groups": {
                "orchesc/a/ns": "/proxy/api/catbox/dych6e"
            },
            "last_updated": 1660957771
        }
    }
}